cogapp/__init__.py
cogapp/__main__.py
cogapp/cogapp.py
cogapp/hashhandler.py
cogapp/makefiles.py
cogapp/test_cogapp.py
cogapp/test_makefiles.py
cogapp/test_whiteutils.py
cogapp/utils.py
cogapp/whiteutils.py
cogapp-3.5.1.dist-info/licenses/AUTHORS.txt
cogapp-3.5.1.dist-info/licenses/LICENSE.txt
cogapp-3.5.1.dist-info/METADATA
cogapp-3.5.1.dist-info/WHEEL
cogapp-3.5.1.dist-info/entry_points.txt
cogapp-3.5.1.dist-info/top_level.txt
cogapp-3.5.1.dist-info/RECORD
